{
    "nodes": [
        {
            "color": "black", 
            "index": 0, 
            "name": "3_1", 
            "label": "3_1"
        }, 
        {
            "color": "black", 
            "index": 1, 
            "name": "3_0", 
            "label": "3_0"
        }, 
        {
            "color": "black", 
            "index": 2, 
            "name": "6_0", 
            "label": "6_0"
        }, 
        {
            "color": "black", 
            "index": 3, 
            "name": "6_1", 
            "label": "6_1"
        }, 
        {
            "color": "black", 
            "index": 4, 
            "name": "node_7", 
            "label": "node_7"
        }, 
        {
            "color": "black", 
            "index": 5, 
            "name": "node_6", 
            "label": "node_6"
        }, 
        {
            "color": "black", 
            "index": 6, 
            "name": "node_5", 
            "label": "node_5"
        }, 
        {
            "color": "black", 
            "index": 7, 
            "name": "node_4", 
            "label": "node_4"
        }, 
        {
            "color": "black", 
            "index": 8, 
            "name": "node_3", 
            "label": "node_3"
        }, 
        {
            "color": "black", 
            "index": 9, 
            "name": "node_2", 
            "label": "node_2"
        }, 
        {
            "color": "black", 
            "index": 10, 
            "name": "node_1", 
            "label": "node_1"
        }, 
        {
            "color": "black", 
            "index": 11, 
            "name": "node_0", 
            "label": "node_0"
        }, 
        {
            "color": "black", 
            "index": 12, 
            "name": "2_0", 
            "label": "2_0"
        }, 
        {
            "color": "black", 
            "index": 13, 
            "name": "5_1", 
            "label": "5_1"
        }, 
        {
            "color": "black", 
            "index": 14, 
            "name": "5_0", 
            "label": "5_0"
        }, 
        {
            "color": "black", 
            "index": 15, 
            "name": "1_1", 
            "label": "1_1"
        }, 
        {
            "color": "black", 
            "index": 16, 
            "name": "1_0", 
            "label": "1_0"
        }, 
        {
            "color": "black", 
            "index": 17, 
            "name": "4_0", 
            "label": "4_0"
        }, 
        {
            "color": "black", 
            "index": 18, 
            "name": "7_1", 
            "label": "7_1"
        }, 
        {
            "color": "black", 
            "index": 19, 
            "name": "7_0", 
            "label": "7_0"
        }, 
        {
            "color": "black", 
            "index": 20, 
            "name": "0_0", 
            "label": "0_0"
        }
    ], 
    "links": [
        {
            "color": "grey", 
            "source": 0, 
            "dash": "5,5", 
            "target": 17, 
            "value": 63.0
        }, 
        {
            "color": "black", 
            "source": 0, 
            "dash": "0,0", 
            "target": 8, 
            "value": 100
        }, 
        {
            "color": "grey", 
            "source": 1, 
            "dash": "5,5", 
            "target": 12, 
            "value": 95.0
        }, 
        {
            "color": "black", 
            "source": 1, 
            "dash": "0,0", 
            "target": 8, 
            "value": 100
        }, 
        {
            "color": "grey", 
            "source": 1, 
            "dash": "5,5", 
            "target": 3, 
            "value": 69.5
        }, 
        {
            "color": "black", 
            "source": 2, 
            "dash": "0,0", 
            "target": 5, 
            "value": 100
        }, 
        {
            "color": "grey", 
            "source": 2, 
            "dash": "5,5", 
            "target": 19, 
            "value": 65.5
        }, 
        {
            "color": "grey", 
            "source": 2, 
            "dash": "5,5", 
            "target": 15, 
            "value": 78.0
        }, 
        {
            "color": "grey", 
            "source": 3, 
            "dash": "5,5", 
            "target": 12, 
            "value": 72.0
        }, 
        {
            "color": "black", 
            "source": 3, 
            "dash": "0,0", 
            "target": 5, 
            "value": 100
        }, 
        {
            "color": "grey", 
            "source": 12, 
            "dash": "5,5", 
            "target": 13, 
            "value": 39.5
        }, 
        {
            "color": "grey", 
            "source": 12, 
            "dash": "5,5", 
            "target": 20, 
            "value": 90.0
        }, 
        {
            "color": "black", 
            "source": 12, 
            "dash": "0,0", 
            "target": 9, 
            "value": 100
        }, 
        {
            "color": "black", 
            "source": 6, 
            "dash": "0,0", 
            "target": 13, 
            "value": 100
        }, 
        {
            "color": "black", 
            "source": 6, 
            "dash": "0,0", 
            "target": 14, 
            "value": 100
        }, 
        {
            "color": "black", 
            "source": 7, 
            "dash": "0,0", 
            "target": 17, 
            "value": 100
        }, 
        {
            "color": "black", 
            "source": 10, 
            "dash": "0,0", 
            "target": 15, 
            "value": 100
        }, 
        {
            "color": "black", 
            "source": 10, 
            "dash": "0,0", 
            "target": 16, 
            "value": 100
        }, 
        {
            "color": "black", 
            "source": 11, 
            "dash": "0,0", 
            "target": 20, 
            "value": 100
        }, 
        {
            "color": "black", 
            "source": 4, 
            "dash": "0,0", 
            "target": 18, 
            "value": 100
        }, 
        {
            "color": "black", 
            "source": 4, 
            "dash": "0,0", 
            "target": 19, 
            "value": 100
        }, 
        {
            "color": "grey", 
            "source": 13, 
            "dash": "5,5", 
            "target": 17, 
            "value": 78.5
        }, 
        {
            "color": "grey", 
            "source": 15, 
            "dash": "5,5", 
            "target": 19, 
            "value": 33.0
        }, 
        {
            "color": "grey", 
            "source": 17, 
            "dash": "5,5", 
            "target": 20, 
            "value": 51.0
        }
    ]
}